CHANGELOG.md
LICENSE
qua/__init__.py
qua/client.py
qua/grpc/__init__.py
qua/grpc/io/__init__.py
qua/grpc/io/qualang/__init__.py
qua/grpc/io/qualang/api/__init__.py
qua/grpc/io/qualang/api/v1.py
qua/info.py
qua/version.py
qua-0.1.0.dist-info/LICENSE
qua-0.1.0.dist-info/WHEEL
qua-0.1.0.dist-info/METADATA
qua-0.1.0.dist-info/RECORD
